vkmania/__init__.py
vkmania/api.py
vkmania/bot.py
vkmania/const.py
vkmania/framework/__init__.py
vkmania/framework/longpoll.py
vkmania/framework/request.py
vkmania/framework/handlers/__init__.py
vkmania/framework/handlers/message.py
vkmania/types/__init__.py
vkmania/types/message.py
vkmania/types/reply.py
vkmania/types/methods/__init__.py
vkmania/types/methods/groups.py
vkmania/types/methods/messages.py
vkmania/types/responses/__init__.py
vkmania/types/responses/groups.py
vkmania/types/responses/messages.py
vkmania-0.0.3.dist-info/LICENSE
vkmania-0.0.3.dist-info/METADATA
vkmania-0.0.3.dist-info/WHEEL
vkmania-0.0.3.dist-info/top_level.txt
vkmania-0.0.3.dist-info/RECORD
