Metadata-Version: 2.1
Name: vkmania
Version: 0.0.3
Summary: Simple VK API wrapper
Home-page: https://github.com/Tazuya/vkmania
Author: Tazuya Shiba
Author-email: deterrisadstellae@mail.ru
License: UNKNOWN
Platform: UNKNOWN
Classifier: Programming Language :: Python :: 3
Classifier: License :: OSI Approved :: MIT License
Classifier: Operating System :: OS Independent
Requires-Python: >=3.6
